pandas_select/__init__.py
pandas_select/_version.py
pandas_select/base.py
pandas_select/bool.py
pandas_select/column.py
pandas_select/iterutils.py
pandas_select/label.py
pandas_select/pandera.py
pandas_select/sklearn.py
pandas_select-0.2.0.dist-info/LICENSE
pandas_select-0.2.0.dist-info/WHEEL
pandas_select-0.2.0.dist-info/METADATA
pandas_select-0.2.0.dist-info/RECORD
