Metadata-Version: 2.1
Name: pandas-select
Version: 0.2.0
Summary: Supercharged DataFrame indexing
Home-page: https://github.com/jeffzi/pandas-select/
License: BSD-3-Clause
Keywords: pandas,scikit-learn
Author: Jean-Francois Zinque
Author-email: jzinque@gmail.com
Requires-Python: >=3.6.1,<3.10
Classifier: Development Status :: 3 - Alpha
Classifier: Environment :: Console
Classifier: Intended Audience :: Science/Research
Classifier: License :: OSI Approved :: BSD License
Classifier: Operating System :: OS Independent
Classifier: Programming Language :: Python
Classifier: Programming Language :: Python :: 3
Classifier: Programming Language :: Python :: 3 :: Only
Classifier: Programming Language :: Python :: 3.6
Classifier: Programming Language :: Python :: 3.7
Classifier: Programming Language :: Python :: 3.8
Classifier: Programming Language :: Python :: 3.9
Classifier: Topic :: Scientific/Engineering
Provides-Extra: docs
Provides-Extra: tests
Requires-Dist: Sphinx (>=3.4.0,<4.0.0); extra == "docs"
Requires-Dist: furo (>=2020.12.9-beta.21,<2021.0.0); extra == "docs"
Requires-Dist: importlib_metadata (>=1.5.0,<2.0.0); python_version < "3.8"
Requires-Dist: ipython (>=7.12.0,<8.0.0); extra == "docs"
Requires-Dist: pandas (>=0.25.3)
Requires-Dist: pandera (>=0.6.0,<0.7.0); extra == "docs" or extra == "tests"
Requires-Dist: pytest (>=6.2.1,<7.0.0); extra == "tests"
Requires-Dist: scikit-learn (>=0.20); extra == "docs" or extra == "tests"
Requires-Dist: sphinx-copybutton (>=0.3.1,<0.4.0)
Requires-Dist: sphinx-panels (>=0.5.2,<0.6.0); extra == "docs"
Requires-Dist: xdoctest (>=0.15.0,<0.16.0); extra == "docs"
Project-URL: Documentation, https://pandas-select.readthedocs.io/
Project-URL: Repository, https://github.com/jeffzi/pandas-select/
